README.md
setup.py
plum_sdk/__init__.py
plum_sdk/models.py
plum_sdk/plum_sdk.py
plum_sdk.egg-info/PKG-INFO
plum_sdk.egg-info/SOURCES.txt
plum_sdk.egg-info/dependency_links.txt
plum_sdk.egg-info/requires.txt
plum_sdk.egg-info/top_level.txt
plum_sdk/tests/__init__.py
plum_sdk/tests/test_data_models.py
plum_sdk/tests/test_dataset_integration.py
plum_sdk/tests/test_dataset_operations.py
plum_sdk/tests/test_exports.py
plum_sdk/tests/test_filtering.py
plum_sdk/tests/test_get_metric.py
plum_sdk/tests/test_iopair.py
plum_sdk/tests/test_list_metrics.py
plum_sdk/tests/test_plum_client.py