Metadata-Version: 2.4
Name: plum_sdk
Version: 1.0.0
Summary: Python SDK for Plum AI
Home-page: https://github.com/getplumai/plum_sdk
Author: Plum AI
Author-email: founders@getplum.ai
Classifier: Programming Language :: Python :: 3
Requires-Python: >=3.6
Requires-Dist: requests
Provides-Extra: dev
Requires-Dist: black; extra == "dev"
Dynamic: author
Dynamic: author-email
Dynamic: classifier
Dynamic: home-page
Dynamic: provides-extra
Dynamic: requires-dist
Dynamic: requires-python
Dynamic: summary
